rh_aws_saml_login/__init__.py
rh_aws_saml_login/__main__.py
rh_aws_saml_login/_api.py
rh_aws_saml_login/_cli.py
rh_aws_saml_login/_consts.py
rh_aws_saml_login/_core.py
rh_aws_saml_login/_exceptions.py
rh_aws_saml_login/_models.py
rh_aws_saml_login/_utils.py
rh_aws_saml_login-0.13.0.dist-info/METADATA
rh_aws_saml_login-0.13.0.dist-info/WHEEL
rh_aws_saml_login-0.13.0.dist-info/entry_points.txt
rh_aws_saml_login-0.13.0.dist-info/RECORD
