Metadata-Version: 2.4
Name: rh-aws-saml-login
Version: 0.13.0
Summary: A CLI tool that allows you to log in and retrieve AWS temporary credentials using Red Hat SAML IDP
Project-URL: homepage, https://github.com/app-sre/rh-aws-saml-login
Project-URL: repository, https://github.com/app-sre/rh-aws-saml-login
Project-URL: documentation, https://github.com/app-sre/rh-aws-saml-login
Project-URL: issues, https://github.com/app-sre/rh-aws-saml-login/issues
Project-URL: changelog, https://github.com/app-sre/rh-aws-saml-login/blob/main/CHANGELOG.md
Author-email: Christian Assing <cassing@redhat.com>
License: MIT License
Classifier: Programming Language :: Python :: 3.11
Classifier: Programming Language :: Python :: 3.12
Classifier: Programming Language :: Python :: 3.13
Classifier: Topic :: Software Development :: Build Tools
Classifier: Topic :: Software Development :: Libraries :: Python Modules
Requires-Python: >=3.11
Requires-Dist: boto3>=1.35.33
Requires-Dist: click<8.4.0
Requires-Dist: humanize>=4.10.0
Requires-Dist: iterfzf>=1.4.0.54.3
Requires-Dist: pyquery>=2.0.1
Requires-Dist: requests-gssapi>=1.4.0
Requires-Dist: rich>=13.9.1
Requires-Dist: typer>=0.16.0
Requires-Dist: tzlocal>=5.2
